pretty_midi_fix/__init__.py
pretty_midi_fix/constants.py
pretty_midi_fix/containers.py
pretty_midi_fix/instrument.py
pretty_midi_fix/pretty_midi.py
pretty_midi_fix/py.typed
pretty_midi_fix/utilities.py
pretty_midi_fix-0.2.0.dist-info/METADATA
pretty_midi_fix-0.2.0.dist-info/WHEEL
pretty_midi_fix-0.2.0.dist-info/RECORD
