Metadata-Version: 2.4
Name: pretty-midi-fix
Version: 0.2.0
Summary: Updated Version of pretty-midi without fluidsynth
Requires-Dist: mido>=1.3.3
Requires-Dist: numpy>=1.7.0
Requires-Dist: six>=1.17.0
